ezpostgres/init.py
ezpostgres/main.py
ezpostgres-0.0.1.dist-info/LICENSE
ezpostgres-0.0.1.dist-info/METADATA
ezpostgres-0.0.1.dist-info/WHEEL
ezpostgres-0.0.1.dist-info/top_level.txt
ezpostgres-0.0.1.dist-info/RECORD
